openrouter/__init__.py
openrouter/_version.py
openrouter/analytics.py
openrouter/api_keys.py
openrouter/basesdk.py
openrouter/beta.py
openrouter/chat.py
openrouter/completions.py
openrouter/credits.py
openrouter/embeddings.py
openrouter/endpoints.py
openrouter/generations.py
openrouter/guardrails.py
openrouter/httpclient.py
openrouter/models_.py
openrouter/oauth.py
openrouter/providers.py
openrouter/py.typed
openrouter/responses.py
openrouter/sdk.py
openrouter/sdkconfiguration.py
openrouter/_hooks/__init__.py
openrouter/_hooks/registration.py
openrouter/_hooks/sdkhooks.py
openrouter/_hooks/types.py
openrouter/components/__init__.py
openrouter/components/_schema0.py
openrouter/components/_schema2.py
openrouter/components/activityitem.py
openrouter/components/assistantmessage.py
openrouter/components/badgatewayresponseerrordata.py
openrouter/components/badrequestresponseerrordata.py
openrouter/components/chatcompletionfinishreason.py
openrouter/components/chaterror.py
openrouter/components/chatgenerationparams.py
openrouter/components/chatgenerationtokenusage.py
openrouter/components/chatmessagecontentitem.py
openrouter/components/chatmessagecontentitemaudio.py
openrouter/components/chatmessagecontentitemcachecontrol.py
openrouter/components/chatmessagecontentitemimage.py
openrouter/components/chatmessagecontentitemtext.py
openrouter/components/chatmessagecontentitemvideo.py
openrouter/components/chatmessagetokenlogprob.py
openrouter/components/chatmessagetokenlogprobs.py
openrouter/components/chatmessagetoolcall.py
openrouter/components/chatresponse.py
openrouter/components/chatresponsechoice.py
openrouter/components/chatstreamingchoice.py
openrouter/components/chatstreamingmessagechunk.py
openrouter/components/chatstreamingmessagetoolcall.py
openrouter/components/chatstreamingresponsechunk.py
openrouter/components/chatstreamoptions.py
openrouter/components/completionchoice.py
openrouter/components/completioncreateparams.py
openrouter-0.1.3.dist-info/licenses/LICENSE
openrouter-0.1.3.dist-info/METADATA
openrouter-0.1.3.dist-info/WHEEL
openrouter-0.1.3.dist-info/top_level.txt
openrouter-0.1.3.dist-info/RECORD
