Metadata-Version: 2.4
Name: openrouter
Version: 0.1.3
Summary: Official Python Client SDK for OpenRouter.
Author: OpenRouter
License: Apache-2.0
Project-URL: repository, https://github.com/OpenRouterTeam/python-sdk.git
Requires-Python: >=3.9.2
License-File: LICENSE
Requires-Dist: httpcore>=1.0.9
Requires-Dist: httpx>=0.28.1
Requires-Dist: pydantic>=2.11.2
Dynamic: license-file
